powerpuff/__init__.py
powerpuff/re.py
powerpuff/rich.py
powerpuff-0.0.2.dist-info/LICENSE
powerpuff-0.0.2.dist-info/LICENSE.txt
powerpuff-0.0.2.dist-info/METADATA
powerpuff-0.0.2.dist-info/WHEEL
powerpuff-0.0.2.dist-info/top_level.txt
powerpuff-0.0.2.dist-info/RECORD
